source_declarative_manifest/__init__.py
source_declarative_manifest/run.py
source_declarative_manifest/spec.json
airbyte_source_declarative_manifest-6.5.2.dist-info/METADATA
airbyte_source_declarative_manifest-6.5.2.dist-info/WHEEL
airbyte_source_declarative_manifest-6.5.2.dist-info/entry_points.txt
airbyte_source_declarative_manifest-6.5.2.dist-info/RECORD
