Metadata-Version: 2.1
Name: airbyte-source-declarative-manifest
Version: 6.5.2
Summary: Base source implementation for low-code sources.
Home-page: https://airbyte.com
License: MIT
Author: Airbyte
Author-email: contact@airbyte.io
Requires-Python: >=3.10,<3.12
Classifier: License :: OSI Approved :: MIT License
Classifier: Programming Language :: Python :: 3
Classifier: Programming Language :: Python :: 3.10
Classifier: Programming Language :: Python :: 3.11
Requires-Dist: airbyte-cdk (==6.5.2)
Project-URL: Documentation, https://docs.airbyte.com/integrations/sources/low-code
Project-URL: Repository, https://github.com/airbytehq/airbyte
